converse_mapper/__init__.py
converse_mapper/bedrock_client.py
converse_mapper/config.py
converse_mapper/content_mappers.py
converse_mapper/doc.py
converse_mapper/mappers.py
converse_mapper/models.py
converse_mapper/transformer.py
converse_mapper/config/ai21/v1.yml
converse_mapper/config/amazon/v1.yml
converse_mapper/config/anthropic/v1.yml
converse_mapper/config/cohere/v1.yml
converse_mapper/config/deepseek/v1.yml
converse_mapper/config/jumpstart/v1.yml
converse_mapper/config/meta/v1.yml
converse_mapper/config/mistral/v1.yml
converse_mapper/config/qwen/v1.yml
converse_mapper/config/writer/v1.yml
converse_mapper-1.0.1.dist-info/licenses/LICENSE.md
converse_mapper-1.0.1.dist-info/METADATA
converse_mapper-1.0.1.dist-info/WHEEL
converse_mapper-1.0.1.dist-info/top_level.txt
converse_mapper-1.0.1.dist-info/RECORD
