Metadata-Version: 2.4
Name: converse-mapper
Version: 1.0.1
Summary: Simple, readable AI model interface transformer for Amazon Bedrock
Author-email: Karthik Kumar Viswanathan <me@karthikkumar.org>, Claude Code <claude@anthropic.com>
License-Expression: MIT
Project-URL: Homepage, https://github.com/guilt/Python-Converse-Mapper
Project-URL: Repository, https://github.com/guilt/Python-Converse-Mapper
Project-URL: Documentation, https://github.com/guilt/Python-Converse-Mapper/blob/main/README.md
Keywords: ai,bedrock,aws,llm,transformer
Classifier: Development Status :: 5 - Production/Stable
Classifier: Intended Audience :: Developers
Classifier: Programming Language :: Python :: 3
Classifier: Programming Language :: Python :: 3.8
Classifier: Programming Language :: Python :: 3.9
Classifier: Programming Language :: Python :: 3.10
Classifier: Programming Language :: Python :: 3.11
Classifier: Programming Language :: Python :: 3.12
Classifier: Programming Language :: Python :: 3.13
Classifier: Topic :: Software Development :: Libraries :: Python Modules
Classifier: Topic :: Scientific/Engineering :: Artificial Intelligence
Requires-Python: >=3.8
License-File: LICENSE.md
Requires-Dist: PyYAML>=6.0.0
Provides-Extra: http
Requires-Dist: requests>=2.25.0; extra == "http"
Provides-Extra: aws
Requires-Dist: boto3>=1.26.0; extra == "aws"
Provides-Extra: dev
Requires-Dist: converse-mapper[aws,http]; extra == "dev"
Requires-Dist: coverage>=7.0.0; extra == "dev"
Requires-Dist: black>=22.0.0; extra == "dev"
Requires-Dist: flake8>=4.0.0; extra == "dev"
Requires-Dist: mypy>=0.950; extra == "dev"
Dynamic: license-file
